anqa/cli/__init__.py
anqa/cli/__main__.py
anqa/cli/_version.py
anqa/cli/app.py
anqa/cli/enum.py
anqa/cli/generator.py
anqa/cli/helpers.py
anqa/cli/templates/api/cookiecutter.json
anqa/cli/templates/api/{{cookiecutter.name}}/__init__.py
anqa/cli/templates/api/{{cookiecutter.name}}/exceptions.py
anqa/cli/templates/api/{{cookiecutter.name}}/handlers.py
anqa/cli/templates/api/{{cookiecutter.name}}/models.py
anqa/cli/templates/api/{{cookiecutter.name}}/repository.py
anqa/cli/templates/api/{{cookiecutter.name}}/router.py
anqa/cli/templates/api/{{cookiecutter.name}}/schemas.py
anqa/cli/templates/api/{{cookiecutter.name}}/views.py
anqa/cli/templates/app/cookiecutter.json
anqa/cli/templates/app/{{cookiecutter.name}}/__init__.py
anqa/cli/templates/app/{{cookiecutter.name}}/api/__init__.py
anqa/cli/templates/app/{{cookiecutter.name}}/api/router.py
anqa/cli/templates/app/{{cookiecutter.name}}/api/tags_metadata.py
anqa/cli/templates/app/{{cookiecutter.name}}/app.py
anqa/cli/templates/app/{{cookiecutter.name}}/asgi.py
anqa/cli/templates/app/{{cookiecutter.name}}/settings.py
anqa/cli/templates/project/cookiecutter.json
anqa/cli/templates/project/hooks/post_gen_project.py
anqa/cli/templates/project/{{cookiecutter.name}}/.flake8
anqa/cli/templates/project/{{cookiecutter.name}}/.pre-commit-config.yaml
anqa/cli/templates/project/{{cookiecutter.name}}/Dockerfile
anqa/cli/templates/project/{{cookiecutter.name}}/Taskfile.yml
anqa/cli/templates/project/{{cookiecutter.name}}/alembic.ini
anqa/cli/templates/project/{{cookiecutter.name}}/docker-compose.yaml
anqa/cli/templates/project/{{cookiecutter.name}}/migrations/env.py
anqa/cli/templates/project/{{cookiecutter.name}}/migrations/script.py.mako
anqa/cli/templates/project/{{cookiecutter.name}}/migrations/versions/.gitkeep
anqa/cli/templates/project/{{cookiecutter.name}}/pyproject.toml
anqa/cli/templates/project/{{cookiecutter.name}}/tests/__init__.py
anqa/cli/templates/project/{{cookiecutter.name}}/tests/conftest.py
anqa_cli-0.0.3.dist-info/METADATA
anqa_cli-0.0.3.dist-info/WHEEL
anqa_cli-0.0.3.dist-info/entry_points.txt
anqa_cli-0.0.3.dist-info/RECORD
