Metadata-Version: 2.1
Name: anqa-cli
Version: 0.0.3
Summary: 
Requires-Python: >=3.8.1,<4.0
Classifier: Programming Language :: Python :: 3
Classifier: Programming Language :: Python :: 3.9
Classifier: Programming Language :: Python :: 3.10
Classifier: Programming Language :: Python :: 3.11
Requires-Dist: cookiecutter (>=2.1.1,<3.0.0)
Requires-Dist: questionary (>=1.10.0,<2.0.0)
Requires-Dist: typer (>=0.7.0,<0.8.0)
